{
  "schema_version": "1.2",
  "timestamp": "2026-05-06 10:10:04",
  "window_start": "2026-05-06 10:00:00",
  "window_end": "2026-05-06 10:59:59",
  "run_source": "schedule",
  "market_signals": {
    "kospi": {
      "price": "7,325.31",
      "change": "▲ 388.32 (+5.60%)",
      "color": "#ef4444",
      "trend": "상승"
    },
    "kosdaq": {
      "price": "1,205.91",
      "change": "▼ 7.83 (-0.65%)",
      "color": "#3b82f6",
      "trend": "하락"
    },
    "sp500": {
      "price": "7,259.22",
      "change": "▲ 58.47 (+0.81%)",
      "color": "#ef4444",
      "trend": "상승"
    },
    "dow": {
      "price": "49,298.25",
      "change": "▲ 356.35 (+0.73%)",
      "color": "#ef4444",
      "trend": "상승"
    },
    "nasdaq": {
      "price": "25,326.12",
      "change": "▲ 258.32 (+1.03%)",
      "color": "#ef4444",
      "trend": "상승"
    },
    "ewy": {
      "price": "173.47",
      "change": "▲ 9.88 (+6.04%)",
      "color": "#ef4444",
      "trend": "상승"
    },
    "vix": {
      "price": "17.38",
      "change": "▼ 0.91 (-4.98%)",
      "color": "#3b82f6",
      "trend": "하락"
    },
    "usdkrw": {
      "price": "1,456.98",
      "change": "▼ 19.07 (-1.29%)",
      "color": "#3b82f6",
      "trend": "하락"
    },
    "us10y": {
      "price": "4.42",
      "change": "▼ 0.03 (-0.67%)",
      "color": "#3b82f6",
      "trend": "하락"
    }
  },
  "events": {
    "news": [
      {
        "source": "뉴시스",
        "title": "\"이제는 K-프리미엄 시대\"…반도체 올라탄 韓증시 '팔천피' 향해 간다[칠천피 시대]",
        "published_at": "2026-05-06 10:00:05",
        "url": "https://finance.naver.com/news/news_read.naver?article_id=0013927350&office_id=003&mode=mainnews&type=&date=2026-05-06&page=1",
        "impact_score": 0,
        "tags": []
      },
      {
        "source": "헤럴드경제",
        "title": "‘7000피’ 뚫자 ‘황제주’ 등극한 SK스퀘어…시총 3위로 ‘껑충’ [종목Pick]",
        "published_at": "2026-05-06 09:56:10",
        "url": "https://finance.naver.com/news/news_read.naver?article_id=0002639396&office_id=016&mode=mainnews&type=&date=2026-05-06&page=1",
        "impact_score": 0,
        "tags": []
      },
      {
        "source": "뉴시스",
        "title": "유종우 한투증권 센터장 \"韓증시 여전히 저평가…에너지·전력·로봇 주목\"[칠천피 시대]",
        "published_at": "2026-05-06 09:55:00",
        "url": "https://finance.naver.com/news/news_read.naver?article_id=0013927325&office_id=003&mode=mainnews&type=&date=2026-05-06&page=1",
        "impact_score": 0,
        "tags": []
      },
      {
        "source": "한국경제TV",
        "title": "코스피 8000 넘본다는데 지갑은 닫혔다…증시-소비 '디커플링' 왜",
        "published_at": "2026-05-06 09:50:43",
        "url": "https://finance.naver.com/news/news_read.naver?article_id=0001251164&office_id=215&mode=mainnews&type=&date=2026-05-06&page=1",
        "impact_score": 0,
        "tags": []
      },
      {
        "source": "헤럴드경제",
        "title": "“반도체 없이 코스피 없다” 코스피 7000 시대, 더 강해진 ‘반도체 의존 장세’ [투자360]",
        "published_at": "2026-05-06 09:45:13",
        "url": "https://finance.naver.com/news/news_read.naver?article_id=0002639385&office_id=016&mode=mainnews&type=&date=2026-05-06&page=1",
        "impact_score": 0,
        "tags": []
      },
      {
        "source": "블로터",
        "title": "① 개미 투자금 1800억 회수 '안갯속'[제이알리츠 회생 쇼크]",
        "published_at": "2026-05-06 09:45:07",
        "url": "https://finance.naver.com/news/news_read.naver?article_id=0000083991&office_id=293&mode=mainnews&type=&date=2026-05-06&page=1",
        "impact_score": 0,
        "tags": []
      },
      {
        "source": "헤럴드경제",
        "title": "“이렇게나 또 오른다고?” 삼전·하닉 장 초반 10% 넘게 급등…최고치 새로 썼다 [종목Pick]",
        "published_at": "2026-05-06 09:43:07",
        "url": "https://finance.naver.com/news/news_read.naver?article_id=0002639381&office_id=016&mode=mainnews&type=&date=2026-05-06&page=1",
        "impact_score": 0,
        "tags": []
      },
      {
        "source": "매일경제",
        "title": "신한운용 ‘AI반도체TOP2플러스 ETF’, 순자산 1조원 돌파",
        "published_at": "2026-05-06 09:41:06",
        "url": "https://finance.naver.com/news/news_read.naver?article_id=0005675716&office_id=009&mode=mainnews&type=&date=2026-05-06&page=1",
        "impact_score": 0,
        "tags": []
      },
      {
        "source": "매일경제",
        "title": "코스피 폭주에 증권주도 불기둥…미래에셋증권 12%대 상승 [매경 자이앤트]",
        "published_at": "2026-05-06 09:40:12",
        "url": "https://finance.naver.com/news/news_read.naver?article_id=0005675715&office_id=009&mode=mainnews&type=&date=2026-05-06&page=1",
        "impact_score": 0,
        "tags": []
      },
      {
        "source": "헤럴드경제",
        "title": "“이게 말이 돼?” 순식간에 7300 찍은 코스피…MSCI·레버리지 ETF까지 주목 [투자360]",
        "published_at": "2026-05-06 09:40:12",
        "url": "https://finance.naver.com/news/news_read.naver?article_id=0002639374&office_id=016&mode=mainnews&type=&date=2026-05-06&page=1",
        "impact_score": 0,
        "tags": []
      },
      {
        "source": "매일경제",
        "title": "떨어질 때마다 물 타던 ‘비트코인 대부’...18조 손실에 “잘못 생각했다”",
        "published_at": "2026-05-06 09:40:09",
        "url": "https://finance.naver.com/news/news_read.naver?article_id=0005675714&office_id=009&mode=mainnews&type=&date=2026-05-06&page=1",
        "impact_score": 0,
        "tags": []
      },
      {
        "source": "아시아경제",
        "title": "코스피 7300 뚫었는데 코스닥은 왜…시총 상위종목 대부분 하락세",
        "published_at": "2026-05-06 09:38:17",
        "url": "https://finance.naver.com/news/news_read.naver?article_id=0005758747&office_id=277&mode=mainnews&type=&date=2026-05-06&page=1",
        "impact_score": 0,
        "tags": []
      },
      {
        "source": "아시아경제",
        "title": "\"팔천피도 충분\" 국내외 증권사들 줄줄이 코스피 전망치 올리는 이유",
        "published_at": "2026-05-06 09:30:11",
        "url": "https://finance.naver.com/news/news_read.naver?article_id=0005758730&office_id=277&mode=mainnews&type=&date=2026-05-06&page=1",
        "impact_score": 0,
        "tags": []
      },
      {
        "source": "한국경제TV",
        "title": "코스피 7천 돌파…개미·반도체 '쌍끌이'",
        "published_at": "2026-05-06 09:29:51",
        "url": "https://finance.naver.com/news/news_read.naver?article_id=0001251158&office_id=215&mode=mainnews&type=&date=2026-05-06&page=1",
        "impact_score": 0,
        "tags": []
      },
      {
        "source": "파이낸셜뉴스",
        "title": "코스피 '7700 시대' 열리나…한투證 \"반도체 이익이 지수 견인\"",
        "published_at": "2026-05-06 09:28:15",
        "url": "https://finance.naver.com/news/news_read.naver?article_id=0005517523&office_id=014&mode=mainnews&type=&date=2026-05-06&page=1",
        "impact_score": 0,
        "tags": []
      },
      {
        "source": "이데일리",
        "title": "삼성액티브운용, 코스닥 핵심 성장주 담은 ‘코스닥FOCUS 펀드’ 출시",
        "published_at": "2026-05-06 09:26:11",
        "url": "https://finance.naver.com/news/news_read.naver?article_id=0006273840&office_id=018&mode=mainnews&type=&date=2026-05-06&page=1",
        "impact_score": 2,
        "tags": [
          "+성장"
        ]
      },
      {
        "source": "헤럴드경제",
        "title": "‘반도체의 힘’, 전쟁도 뚫고 ‘칠천피’ 만들었다…“이달 내 7700도 가능” [투자360]",
        "published_at": "2026-05-06 09:26:10",
        "url": "https://finance.naver.com/news/news_read.naver?article_id=0002639355&office_id=016&mode=mainnews&type=&date=2026-05-06&page=1",
        "impact_score": 0,
        "tags": []
      },
      {
        "source": "이데일리",
        "title": "'파죽지세' 코스피 5%대 급등 7300선…삼전닉스도 8%↑ '신고가'[7000피 시대]",
        "published_at": "2026-05-06 09:23:07",
        "url": "https://finance.naver.com/news/news_read.naver?article_id=0006273835&office_id=018&mode=mainnews&type=&date=2026-05-06&page=1",
        "impact_score": 0,
        "tags": []
      },
      {
        "source": "아시아경제",
        "title": "신한운용, SOL AI반도체TOP2플러스 순자산 1조원 돌파",
        "published_at": "2026-05-06 09:22:19",
        "url": "https://finance.naver.com/news/news_read.naver?article_id=0005758717&office_id=277&mode=mainnews&type=&date=2026-05-06&page=1",
        "impact_score": 0,
        "tags": []
      },
      {
        "source": "머니투데이",
        "title": "꿈의 '7천피' 1등 공신...25만전자·160만닉스 랠리",
        "published_at": "2026-05-06 09:22:01",
        "url": "https://finance.naver.com/news/news_read.naver?article_id=0005353349&office_id=008&mode=mainnews&type=&date=2026-05-06&page=1",
        "impact_score": 0,
        "tags": []
      }
    ],
    "dart": [
      {
        "corp_name": "지피아이",
        "title": "연결감사보고서 (2025.12)",
        "published_at": "20260506",
        "url": "https://dart.fss.or.kr/dsaf001/main.do?rcpNo=20260506000056",
        "impact_score": 0,
        "tags": []
      },
      {
        "corp_name": "나노",
        "title": "기업설명회(IR)개최              ",
        "published_at": "20260506",
        "url": "https://dart.fss.or.kr/dsaf001/main.do?rcpNo=20260506900201",
        "impact_score": 0,
        "tags": []
      },
      {
        "corp_name": "청라플러스",
        "title": "감사보고서 (2025.12)",
        "published_at": "20260506",
        "url": "https://dart.fss.or.kr/dsaf001/main.do?rcpNo=20260506000054",
        "impact_score": 0,
        "tags": []
      },
      {
        "corp_name": "렛츠밀란커머스",
        "title": "감사보고서 (2025.12)",
        "published_at": "20260506",
        "url": "https://dart.fss.or.kr/dsaf001/main.do?rcpNo=20260506000053",
        "impact_score": 0,
        "tags": []
      },
      {
        "corp_name": "컬리",
        "title": "주요사항보고서(유상증자결정)",
        "published_at": "20260506",
        "url": "https://dart.fss.or.kr/dsaf001/main.do?rcpNo=20260506000052",
        "impact_score": -4,
        "tags": [
          "-유상증자"
        ]
      },
      {
        "corp_name": "와이오씨디벨로퍼",
        "title": "감사보고서 (2025.12)",
        "published_at": "20260506",
        "url": "https://dart.fss.or.kr/dsaf001/main.do?rcpNo=20260506000048",
        "impact_score": 0,
        "tags": []
      },
      {
        "corp_name": "포인트모바일",
        "title": "자기주식처분결과보고서",
        "published_at": "20260506",
        "url": "https://dart.fss.or.kr/dsaf001/main.do?rcpNo=20260506000047",
        "impact_score": 0,
        "tags": []
      },
      {
        "corp_name": "LG씨엔에스",
        "title": "기업설명회(IR)개최(안내공시)              ",
        "published_at": "20260506",
        "url": "https://dart.fss.or.kr/dsaf001/main.do?rcpNo=20260506800189",
        "impact_score": 0,
        "tags": []
      },
      {
        "corp_name": "한화손해보험",
        "title": "임원ㆍ주요주주특정증권등소유상황보고서",
        "published_at": "20260506",
        "url": "https://dart.fss.or.kr/dsaf001/main.do?rcpNo=20260506000043",
        "impact_score": 0,
        "tags": []
      },
      {
        "corp_name": "LG씨엔에스",
        "title": "기업설명회(IR)개최(안내공시)              ",
        "published_at": "20260506",
        "url": "https://dart.fss.or.kr/dsaf001/main.do?rcpNo=20260506800185",
        "impact_score": 0,
        "tags": []
      },
      {
        "corp_name": "미코",
        "title": "주식등의대량보유상황보고서(약식)",
        "published_at": "20260506",
        "url": "https://dart.fss.or.kr/dsaf001/main.do?rcpNo=20260506000040",
        "impact_score": 0,
        "tags": []
      },
      {
        "corp_name": "우경",
        "title": "감사보고서 (2025.12)",
        "published_at": "20260506",
        "url": "https://dart.fss.or.kr/dsaf001/main.do?rcpNo=20260506000038",
        "impact_score": 0,
        "tags": []
      },
      {
        "corp_name": "천일산업",
        "title": "감사보고서 (2025.12)",
        "published_at": "20260506",
        "url": "https://dart.fss.or.kr/dsaf001/main.do?rcpNo=20260506000035",
        "impact_score": 0,
        "tags": []
      },
      {
        "corp_name": "THE CUBE&",
        "title": "임원ㆍ주요주주특정증권등소유상황보고서",
        "published_at": "20260506",
        "url": "https://dart.fss.or.kr/dsaf001/main.do?rcpNo=20260506000034",
        "impact_score": 0,
        "tags": []
      },
      {
        "corp_name": "NAVER",
        "title": "기업설명회(IR)개최(안내공시)              ",
        "published_at": "20260506",
        "url": "https://dart.fss.or.kr/dsaf001/main.do?rcpNo=20260506800183",
        "impact_score": 0,
        "tags": []
      },
      {
        "corp_name": "한국타키겐제조",
        "title": "감사보고서 (2026.01)",
        "published_at": "20260506",
        "url": "https://dart.fss.or.kr/dsaf001/main.do?rcpNo=20260506000027",
        "impact_score": 0,
        "tags": []
      },
      {
        "corp_name": "세원전자",
        "title": "연결감사보고서 (2025.12)",
        "published_at": "20260506",
        "url": "https://dart.fss.or.kr/dsaf001/main.do?rcpNo=20260506000024",
        "impact_score": 0,
        "tags": []
      },
      {
        "corp_name": "지역난방공사",
        "title": "기업설명회(IR)개최(안내공시)              ",
        "published_at": "20260506",
        "url": "https://dart.fss.or.kr/dsaf001/main.do?rcpNo=20260506800174",
        "impact_score": 0,
        "tags": []
      },
      {
        "corp_name": "대창솔루션",
        "title": "연결재무제표기준영업(잠정)실적(공정공시)              ",
        "published_at": "20260506",
        "url": "https://dart.fss.or.kr/dsaf001/main.do?rcpNo=20260506900162",
        "impact_score": 0,
        "tags": []
      },
      {
        "corp_name": "동원개발",
        "title": "임원ㆍ주요주주특정증권등소유상황보고서",
        "published_at": "20260506",
        "url": "https://dart.fss.or.kr/dsaf001/main.do?rcpNo=20260506000022",
        "impact_score": 0,
        "tags": []
      },
      {
        "corp_name": "씨젠",
        "title": "자기주식처분결과보고서",
        "published_at": "20260506",
        "url": "https://dart.fss.or.kr/dsaf001/main.do?rcpNo=20260506000021",
        "impact_score": 0,
        "tags": []
      },
      {
        "corp_name": "지역난방공사",
        "title": "결산실적공시예고(안내공시)              ",
        "published_at": "20260506",
        "url": "https://dart.fss.or.kr/dsaf001/main.do?rcpNo=20260506800164",
        "impact_score": 0,
        "tags": []
      },
      {
        "corp_name": "동원개발",
        "title": "주식등의대량보유상황보고서(일반)",
        "published_at": "20260506",
        "url": "https://dart.fss.or.kr/dsaf001/main.do?rcpNo=20260506000019",
        "impact_score": 0,
        "tags": []
      },
      {
        "corp_name": "대창솔루션",
        "title": "영업(잠정)실적(공정공시)              ",
        "published_at": "20260506",
        "url": "https://dart.fss.or.kr/dsaf001/main.do?rcpNo=20260506900152",
        "impact_score": 0,
        "tags": []
      },
      {
        "corp_name": "대창모터스",
        "title": "감사보고서 (2025.12)",
        "published_at": "20260506",
        "url": "https://dart.fss.or.kr/dsaf001/main.do?rcpNo=20260506000014",
        "impact_score": 0,
        "tags": []
      },
      {
        "corp_name": "에스엠",
        "title": "기업설명회(IR)개최              ",
        "published_at": "20260506",
        "url": "https://dart.fss.or.kr/dsaf001/main.do?rcpNo=20260506900146",
        "impact_score": 0,
        "tags": []
      },
      {
        "corp_name": "ISC",
        "title": "기업설명회(IR)개최              ",
        "published_at": "20260506",
        "url": "https://dart.fss.or.kr/dsaf001/main.do?rcpNo=20260506900144",
        "impact_score": 0,
        "tags": []
      },
      {
        "corp_name": "디비수성스위첸유동화전문유한회사",
        "title": "자산유동화관련중요사항발생등보고서(기타)",
        "published_at": "20260506",
        "url": "https://dart.fss.or.kr/dsaf001/main.do?rcpNo=20260506000004",
        "impact_score": 0,
        "tags": []
      },
      {
        "corp_name": "DB하이텍",
        "title": "연결재무제표기준영업(잠정)실적(공정공시)              ",
        "published_at": "20260506",
        "url": "https://dart.fss.or.kr/dsaf001/main.do?rcpNo=20260506800098",
        "impact_score": 0,
        "tags": []
      },
      {
        "corp_name": "마키나락스",
        "title": "투자설명서",
        "published_at": "20260506",
        "url": "https://dart.fss.or.kr/dsaf001/main.do?rcpNo=20260506000003",
        "impact_score": 0,
        "tags": []
      },
      {
        "corp_name": "셀트리온",
        "title": "주식소각결정              ",
        "published_at": "20260506",
        "url": "https://dart.fss.or.kr/dsaf001/main.do?rcpNo=20260506800095",
        "impact_score": 0,
        "tags": []
      },
      {
        "corp_name": "셀트리온",
        "title": "연결재무제표기준영업(잠정)실적(공정공시)              ",
        "published_at": "20260506",
        "url": "https://dart.fss.or.kr/dsaf001/main.do?rcpNo=20260506800093",
        "impact_score": 0,
        "tags": []
      },
      {
        "corp_name": "유가증권시장본부",
        "title": "기타시장안내(금일NXT경쟁매매대상종목지정으로인한KRX시간외단일가매매제외종목안내(유가증권시장))              ",
        "published_at": "20260506",
        "url": "https://dart.fss.or.kr/dsaf001/main.do?rcpNo=20260506800019",
        "impact_score": 0,
        "tags": []
      },
      {
        "corp_name": "대한조선",
        "title": "기업설명회(IR)개최(안내공시)              ",
        "published_at": "20260506",
        "url": "https://dart.fss.or.kr/dsaf001/main.do?rcpNo=20260506800021",
        "impact_score": 0,
        "tags": []
      },
      {
        "corp_name": "코스닥시장본부",
        "title": "기타시장안내(금일NXT경쟁매매대상종목지정으로인한KRX시간외단일가매매제외종목안내(코스닥시장))              ",
        "published_at": "20260506",
        "url": "https://dart.fss.or.kr/dsaf001/main.do?rcpNo=20260506900018",
        "impact_score": 0,
        "tags": []
      },
      {
        "corp_name": "카카오뱅크",
        "title": "영업(잠정)실적(공정공시)              ",
        "published_at": "20260506",
        "url": "https://dart.fss.or.kr/dsaf001/main.do?rcpNo=20260506800005",
        "impact_score": 0,
        "tags": []
      },
      {
        "corp_name": "마키나락스",
        "title": "효력발생안내( 2026.4.10. 제출 증권신고서(지분증권) )",
        "published_at": "20260506",
        "url": "https://dart.fss.or.kr/dsaf001/main.do?rcpNo=20260410100007",
        "impact_score": 0,
        "tags": []
      },
      {
        "corp_name": "우리금융지주",
        "title": "효력발생안내( 2026.4.24. 제출 일괄신고서 )",
        "published_at": "20260506",
        "url": "https://dart.fss.or.kr/dsaf001/main.do?rcpNo=20260424100005",
        "impact_score": 0,
        "tags": []
      },
      {
        "corp_name": "한화투자증권",
        "title": "증권발행실적보고서",
        "published_at": "20260506",
        "url": "https://dart.fss.or.kr/dsaf001/main.do?rcpNo=20260504000461",
        "impact_score": 0,
        "tags": []
      }
    ],
    "news_count": 20,
    "dart_count": 39
  },
  "sentiment": {
    "raw_score": 1.46,
    "score": 51.0,
    "raw_label": "neutral",
    "label": "중립",
    "range_key": "neutral",
    "range_rule": "40~59.9는 중립 구간",
    "interpretation": "상승·하락 신호가 혼재한 상태입니다.",
    "confidence": 95,
    "market_score": 12,
    "news_score": 2.0,
    "dart_score": -4.0,
    "sector_score": 1.07,
    "normalized_components": {
      "market": 1.1003,
      "news": -0.6485,
      "dart": -2.698,
      "sector": 1.4374
    },
    "weights": {
      "market": 0.4,
      "news": 0.2,
      "dart": 0.2,
      "sector": 0.2
    },
    "model_version": "v2.0-calibrated",
    "calibration_metric": 0.5455,
    "calibration_samples": 44,
    "score_breakdown": {
      "market": 12,
      "news": 2.0,
      "dart": -4.0,
      "sector": 1.07
    },
    "tooltip_breakdown": "시장 12 / 뉴스 2.0 / 공시 -4.0 / 섹터 1.07",
    "data_quality": {
      "live_indexes": 9,
      "event_count": 59,
      "sector_confirmed": 6,
      "score": 95,
      "basis": "지표 9/9, 이벤트 59건, 섹터확인 6건"
    },
    "confidence_tooltip": [
      "신뢰도 안내",
      "신뢰도는 예측 적중률이 아니라, 현재 점수 계산에 사용된 데이터의 충실도를 의미합니다.",
      "현재 신뢰도: 95%",
      "해석: 데이터 커버리지가 높은 상태입니다.",
      "기준: 지표 9/9, 이벤트 59건, 섹터확인 6건",
      "주의: 이 값이 미래 방향 적중률을 직접 뜻하지는 않습니다."
    ]
  },
  "key_points": [
    "KOSPI는 7,325.31로 5.60% 상승하며 강세를 보이고 있으며, KOSDAQ은 1,205.91로 0.65% 하락 중입니다.",
    "삼성액티브운용이 **코스닥FOCUS 펀드**를 출시하며, 코스닥 성장주에 대한 관심이 높아지고 있습니다.",
    "VIX는 17.38로 4.98% 하락하여 시장의 변동성이 다소 줄어든 상황입니다."
  ],
  "watchpoint": "오늘의 핵심 관전 포인트: KOSPI의 상승세가 지속될지 여부가 **주요 관전 포인트**입니다.",
  "day_over_day": [
    "전일 동시간 대비 **센티먼트 -18.60p** 변화로 현재 점수는 51.0점입니다.",
    "리스크 축은 **VIX 0.0**, **달러원 -17.9** 만큼 변동했습니다.",
    "이벤트 발생량은 전일 대비 **+28건** 차이로 뉴스/공시 민감도를 점검할 구간입니다."
  ],
  "sector_rotation": {
    "scores": [
      {
        "sector": "반도체",
        "mentions": 7,
        "event_score": 0.0,
        "price_confirmation": 10.5,
        "breadth": 0,
        "final_score": 2.0,
        "confidence": 85,
        "price_confirmed": true,
        "representatives": [
          "삼성전자 +11.40%",
          "SK하이닉스 +9.61%"
        ],
        "matched_titles": [
          "\"이제는 K-프리미엄 시대\"…반도체 올라탄 韓증시 '팔천피' 향해 간다[칠천피 시대]",
          "“반도체 없이 코스피 없다” 코스피 7000 시대, 더 강해진 ‘반도체 의존 장세’ [투자360]",
          "신한운용 ‘AI반도체TOP2플러스 ETF’, 순자산 1조원 돌파"
        ]
      },
      {
        "sector": "금융",
        "mentions": 10,
        "event_score": 0.0,
        "price_confirmation": 1.88,
        "breadth": 0,
        "final_score": 1.26,
        "confidence": 85,
        "price_confirmed": true,
        "representatives": [
          "KB금융 +2.34%",
          "신한지주 +1.43%"
        ],
        "matched_titles": [
          "유종우 한투증권 센터장 \"韓증시 여전히 저평가…에너지·전력·로봇 주목\"[칠천피 시대]",
          "코스피 폭주에 증권주도 불기둥…미래에셋증권 12%대 상승 [매경 자이앤트]",
          "\"팔천피도 충분\" 국내외 증권사들 줄줄이 코스피 전망치 올리는 이유"
        ]
      },
      {
        "sector": "바이오",
        "mentions": 0,
        "event_score": 0.0,
        "price_confirmation": -0.09,
        "breadth": 0,
        "final_score": -0.06,
        "confidence": 45,
        "price_confirmed": true,
        "representatives": [
          "삼성바이오로직스 -0.74%",
          "셀트리온 +0.56%"
        ],
        "matched_titles": []
      },
      {
        "sector": "2차전지",
        "mentions": 0,
        "event_score": 0.0,
        "price_confirmation": -0.93,
        "breadth": 0,
        "final_score": -0.62,
        "confidence": 45,
        "price_confirmed": true,
        "representatives": [
          "LG에너지솔루션 +0.21%",
          "삼성SDI -2.06%"
        ],
        "matched_titles": []
      },
      {
        "sector": "방산",
        "mentions": 0,
        "event_score": 0.0,
        "price_confirmation": -1.22,
        "breadth": 0,
        "final_score": -0.81,
        "confidence": 45,
        "price_confirmed": true,
        "representatives": [
          "한화에어로스페이스 -1.16%",
          "한국항공우주 -1.28%"
        ],
        "matched_titles": []
      },
      {
        "sector": "에너지",
        "mentions": 2,
        "event_score": 0.0,
        "price_confirmation": -3.37,
        "breadth": 0,
        "final_score": -2.0,
        "confidence": 65,
        "price_confirmed": true,
        "representatives": [
          "SK이노베이션 -2.75%",
          "S-Oil -3.98%"
        ],
        "matched_titles": [
          "유종우 한투증권 센터장 \"韓증시 여전히 저평가…에너지·전력·로봇 주목\"[칠천피 시대]",
          "기타시장안내(금일NXT경쟁매매대상종목지정으로인한KRX시간외단일가매매제외종목안내(유가증권시장))              "
        ]
      }
    ],
    "strong": [
      {
        "sector": "반도체",
        "mentions": 7,
        "event_score": 0.0,
        "price_confirmation": 10.5,
        "breadth": 0,
        "final_score": 2.0,
        "confidence": 85,
        "price_confirmed": true,
        "representatives": [
          "삼성전자 +11.40%",
          "SK하이닉스 +9.61%"
        ],
        "matched_titles": [
          "\"이제는 K-프리미엄 시대\"…반도체 올라탄 韓증시 '팔천피' 향해 간다[칠천피 시대]",
          "“반도체 없이 코스피 없다” 코스피 7000 시대, 더 강해진 ‘반도체 의존 장세’ [투자360]",
          "신한운용 ‘AI반도체TOP2플러스 ETF’, 순자산 1조원 돌파"
        ]
      },
      {
        "sector": "금융",
        "mentions": 10,
        "event_score": 0.0,
        "price_confirmation": 1.88,
        "breadth": 0,
        "final_score": 1.26,
        "confidence": 85,
        "price_confirmed": true,
        "representatives": [
          "KB금융 +2.34%",
          "신한지주 +1.43%"
        ],
        "matched_titles": [
          "유종우 한투증권 센터장 \"韓증시 여전히 저평가…에너지·전력·로봇 주목\"[칠천피 시대]",
          "코스피 폭주에 증권주도 불기둥…미래에셋증권 12%대 상승 [매경 자이앤트]",
          "\"팔천피도 충분\" 국내외 증권사들 줄줄이 코스피 전망치 올리는 이유"
        ]
      }
    ],
    "weak": [
      {
        "sector": "에너지",
        "mentions": 2,
        "event_score": 0.0,
        "price_confirmation": -3.37,
        "breadth": 0,
        "final_score": -2.0,
        "confidence": 65,
        "price_confirmed": true,
        "representatives": [
          "SK이노베이션 -2.75%",
          "S-Oil -3.98%"
        ],
        "matched_titles": [
          "유종우 한투증권 센터장 \"韓증시 여전히 저평가…에너지·전력·로봇 주목\"[칠천피 시대]",
          "기타시장안내(금일NXT경쟁매매대상종목지정으로인한KRX시간외단일가매매제외종목안내(유가증권시장))              "
        ]
      }
    ],
    "basis": "이벤트 점수 + 대표 종목 수익률 확인 결합"
  },
  "reliability": {
    "evaluated": 148,
    "hit_rate": "48.0%",
    "false_alarm_rate": "52.0%",
    "by_label": {
      "bullish": "25.7%",
      "bearish": "11.8%",
      "neutral": "62.5%"
    },
    "basis": "현재 시그널 이후 다음 슬롯의 KOSPI/KOSDAQ 변동률 개선 여부 기준"
  },
  "heatmap": {
    "slots": [
      "08:30",
      "09:30",
      "10:30",
      "11:30",
      "12:30",
      "13:30",
      "14:30",
      "15:30"
    ],
    "rows": [
      {
        "day": "04-30",
        "scores": [
          {
            "slot": "08:30",
            "text": "43",
            "color": "#e2e8f0",
            "state": "neutral"
          },
          {
            "slot": "09:30",
            "text": "-",
            "color": "#f8fafc",
            "state": "missing"
          },
          {
            "slot": "10:30",
            "text": "52",
            "color": "#e2e8f0",
            "state": "neutral"
          },
          {
            "slot": "11:30",
            "text": "54",
            "color": "#e2e8f0",
            "state": "neutral"
          },
          {
            "slot": "12:30",
            "text": "68",
            "color": "#fee2e2",
            "state": "bullish"
          },
          {
            "slot": "13:30",
            "text": "-",
            "color": "#f8fafc",
            "state": "missing"
          },
          {
            "slot": "14:30",
            "text": "52",
            "color": "#e2e8f0",
            "state": "neutral"
          },
          {
            "slot": "15:30",
            "text": "-",
            "color": "#f8fafc",
            "state": "missing"
          }
        ]
      },
      {
        "day": "05-01",
        "scores": [
          {
            "slot": "08:30",
            "text": "47",
            "color": "#e2e8f0",
            "state": "neutral"
          },
          {
            "slot": "09:30",
            "text": "-",
            "color": "#f8fafc",
            "state": "missing"
          },
          {
            "slot": "10:30",
            "text": "49",
            "color": "#e2e8f0",
            "state": "neutral"
          },
          {
            "slot": "11:30",
            "text": "44",
            "color": "#e2e8f0",
            "state": "neutral"
          },
          {
            "slot": "12:30",
            "text": "46",
            "color": "#e2e8f0",
            "state": "neutral"
          },
          {
            "slot": "13:30",
            "text": "-",
            "color": "#f8fafc",
            "state": "missing"
          },
          {
            "slot": "14:30",
            "text": "43",
            "color": "#e2e8f0",
            "state": "neutral"
          },
          {
            "slot": "15:30",
            "text": "-",
            "color": "#f8fafc",
            "state": "missing"
          }
        ]
      },
      {
        "day": "05-04",
        "scores": [
          {
            "slot": "08:30",
            "text": "59",
            "color": "#e2e8f0",
            "state": "neutral"
          },
          {
            "slot": "09:30",
            "text": "-",
            "color": "#f8fafc",
            "state": "missing"
          },
          {
            "slot": "10:30",
            "text": "66",
            "color": "#fee2e2",
            "state": "bullish"
          },
          {
            "slot": "11:30",
            "text": "51",
            "color": "#e2e8f0",
            "state": "neutral"
          },
          {
            "slot": "12:30",
            "text": "48",
            "color": "#e2e8f0",
            "state": "neutral"
          },
          {
            "slot": "13:30",
            "text": "-",
            "color": "#f8fafc",
            "state": "missing"
          },
          {
            "slot": "14:30",
            "text": "44",
            "color": "#e2e8f0",
            "state": "neutral"
          },
          {
            "slot": "15:30",
            "text": "-",
            "color": "#f8fafc",
            "state": "missing"
          }
        ]
      },
      {
        "day": "05-05",
        "scores": [
          {
            "slot": "08:30",
            "text": "37",
            "color": "#dbeafe",
            "state": "caution"
          },
          {
            "slot": "09:30",
            "text": "-",
            "color": "#f8fafc",
            "state": "missing"
          },
          {
            "slot": "10:30",
            "text": "40",
            "color": "#dbeafe",
            "state": "caution"
          },
          {
            "slot": "11:30",
            "text": "54",
            "color": "#e2e8f0",
            "state": "neutral"
          },
          {
            "slot": "12:30",
            "text": "48",
            "color": "#e2e8f0",
            "state": "neutral"
          },
          {
            "slot": "13:30",
            "text": "-",
            "color": "#f8fafc",
            "state": "missing"
          },
          {
            "slot": "14:30",
            "text": "49",
            "color": "#e2e8f0",
            "state": "neutral"
          },
          {
            "slot": "15:30",
            "text": "62",
            "color": "#fee2e2",
            "state": "bullish"
          }
        ]
      },
      {
        "day": "05-06",
        "scores": [
          {
            "slot": "08:30",
            "text": "70",
            "color": "#fee2e2",
            "state": "bullish"
          },
          {
            "slot": "09:30",
            "text": "-",
            "color": "#f8fafc",
            "state": "missing"
          },
          {
            "slot": "10:30",
            "text": "51",
            "color": "#e2e8f0",
            "state": "neutral"
          },
          {
            "slot": "11:30",
            "text": "-",
            "color": "#f8fafc",
            "state": "missing"
          },
          {
            "slot": "12:30",
            "text": "-",
            "color": "#f8fafc",
            "state": "missing"
          },
          {
            "slot": "13:30",
            "text": "-",
            "color": "#f8fafc",
            "state": "missing"
          },
          {
            "slot": "14:30",
            "text": "-",
            "color": "#f8fafc",
            "state": "missing"
          },
          {
            "slot": "15:30",
            "text": "-",
            "color": "#f8fafc",
            "state": "missing"
          }
        ]
      }
    ],
    "timeline": [
      {
        "time": "05-04 12:45",
        "score": 48.2,
        "label": "중립",
        "color": "#e2e8f0"
      },
      {
        "time": "05-04 14:42",
        "score": 44.2,
        "label": "중립",
        "color": "#e2e8f0"
      },
      {
        "time": "05-04 16:31",
        "score": 58.4,
        "label": "중립",
        "color": "#e2e8f0"
      },
      {
        "time": "05-05 08:49",
        "score": 37.4,
        "label": "경계",
        "color": "#dbeafe"
      },
      {
        "time": "05-05 10:08",
        "score": 39.9,
        "label": "경계",
        "color": "#dbeafe"
      },
      {
        "time": "05-05 11:17",
        "score": 53.8,
        "label": "중립",
        "color": "#e2e8f0"
      },
      {
        "time": "05-05 12:43",
        "score": 47.9,
        "label": "중립",
        "color": "#e2e8f0"
      },
      {
        "time": "05-05 14:29",
        "score": 48.8,
        "label": "중립",
        "color": "#e2e8f0"
      },
      {
        "time": "05-05 15:20",
        "score": 61.7,
        "label": "우호",
        "color": "#fee2e2"
      },
      {
        "time": "05-05 16:16",
        "score": 47.5,
        "label": "중립",
        "color": "#e2e8f0"
      },
      {
        "time": "05-06 08:48",
        "score": 69.6,
        "label": "우호",
        "color": "#fee2e2"
      },
      {
        "time": "05-06 10:10",
        "score": 51.0,
        "label": "중립",
        "color": "#e2e8f0"
      }
    ],
    "legend": [
      {
        "name": "강한 우호 80+",
        "color": "#fecaca"
      },
      {
        "name": "우호 60~79",
        "color": "#fee2e2"
      },
      {
        "name": "중립 40~59",
        "color": "#e2e8f0"
      },
      {
        "name": "경계 20~39",
        "color": "#dbeafe"
      },
      {
        "name": "강한 경계 0~19",
        "color": "#bfdbfe"
      },
      {
        "name": "결측",
        "color": "#f8fafc"
      }
    ]
  },
  "calibration": {
    "stats": {
      "market": {
        "median": 3.55,
        "scale": 7.6799,
        "p02": -9.5804,
        "p98": 12.0
      },
      "news": {
        "median": 4.5,
        "scale": 3.8548,
        "p02": -3.8,
        "p98": 11.872
      },
      "dart": {
        "median": 0.0,
        "scale": 1.4826,
        "p02": -7.62,
        "p98": 8.128
      },
      "sector": {
        "median": 0.47,
        "scale": 0.4151,
        "p02": 0.0,
        "p98": 2.0932
      }
    },
    "weights": {
      "market": 0.4,
      "news": 0.2,
      "dart": 0.2,
      "sector": 0.2
    },
    "metric": 0.5455,
    "samples": 44,
    "model_version": "v2.0-calibrated",
    "mode": "calibrated_grid_search"
  },
  "validation_basis": "현재 시그널 이후 다음 슬롯의 KOSPI/KOSDAQ 변동률 개선 여부 기준"
}