{
  "schema_version": "1.2",
  "timestamp": "2026-03-31 10:00:24",
  "window_start": "2026-03-31 10:00:00",
  "window_end": "2026-03-31 10:59:59",
  "run_source": "schedule",
  "market_signals": {
    "kospi": {
      "price": "5,145.69",
      "change": "▼ 131.61 (-2.49%)",
      "color": "#3b82f6",
      "trend": "하락"
    },
    "kosdaq": {
      "price": "1,078.66",
      "change": "▼ 28.39 (-2.56%)",
      "color": "#3b82f6",
      "trend": "하락"
    },
    "sp500": {
      "price": "6,343.72",
      "change": "▼ 25.13 (-0.39%)",
      "color": "#3b82f6",
      "trend": "하락"
    },
    "dow": {
      "price": "45,216.14",
      "change": "▲ 49.50 (+0.11%)",
      "color": "#ef4444",
      "trend": "상승"
    },
    "nasdaq": {
      "price": "20,794.64",
      "change": "▼ 153.72 (-0.73%)",
      "color": "#3b82f6",
      "trend": "하락"
    },
    "ewy": {
      "price": "116.43",
      "change": "▼ 4.55 (-3.76%)",
      "color": "#3b82f6",
      "trend": "하락"
    },
    "vix": {
      "price": "30.61",
      "change": "▼ 0.44 (-1.42%)",
      "color": "#3b82f6",
      "trend": "하락"
    },
    "usdkrw": {
      "price": "1,526.28",
      "change": "▲ 19.26 (+1.28%)",
      "color": "#ef4444",
      "trend": "상승"
    },
    "us10y": {
      "price": "4.34",
      "change": "▼ 0.10 (-2.21%)",
      "color": "#3b82f6",
      "trend": "하락"
    }
  },
  "events": {
    "news": [
      {
        "source": "매일경제",
        "title": "월가 큰손 “저점 매수기회”라는데…코인주 올들어 최악 약세",
        "published_at": "2026-03-31 09:54:14",
        "url": "https://finance.naver.com/news/news_read.naver?article_id=0005658538&office_id=009&mode=mainnews&type=&date=2026-03-31&page=1",
        "impact_score": 1,
        "tags": [
          "+매수"
        ]
      },
      {
        "source": "서울경제",
        "title": "“고점 왔나”…20% 급락한 삼천당제약, 황제주 반납 [이런국장 저런주식]",
        "published_at": "2026-03-31 09:51:10",
        "url": "https://finance.naver.com/news/news_read.naver?article_id=0004605303&office_id=011&mode=mainnews&type=&date=2026-03-31&page=1",
        "impact_score": -3,
        "tags": [
          "-급락"
        ]
      },
      {
        "source": "한국경제",
        "title": "코스피, 전쟁 이후 장중 최저치로 떨어져…반도체株 급락",
        "published_at": "2026-03-31 09:50:15",
        "url": "https://finance.naver.com/news/news_read.naver?article_id=0005268991&office_id=015&mode=mainnews&type=&date=2026-03-31&page=1",
        "impact_score": -3,
        "tags": [
          "-급락"
        ]
      },
      {
        "source": "한국경제TV",
        "title": "운용전략 안 지켜도 그만 [수상한액티브②]",
        "published_at": "2026-03-31 09:35:33",
        "url": "https://finance.naver.com/news/news_read.naver?article_id=0001247256&office_id=215&mode=mainnews&type=&date=2026-03-31&page=1",
        "impact_score": 0,
        "tags": []
      },
      {
        "source": "매일경제",
        "title": "“이러다 5천피도 위태”…코스피 4%대 급락 5100선 붕괴",
        "published_at": "2026-03-31 09:33:09",
        "url": "https://finance.naver.com/news/news_read.naver?article_id=0005658512&office_id=009&mode=mainnews&type=&date=2026-03-31&page=1",
        "impact_score": -3,
        "tags": [
          "-급락"
        ]
      },
      {
        "source": "이데일리",
        "title": "“코스닥 핵심”…TIGER 기술이전바이오액티브, 순자산 1000억 돌파",
        "published_at": "2026-03-31 09:31:10",
        "url": "https://finance.naver.com/news/news_read.naver?article_id=0006246073&office_id=018&mode=mainnews&type=&date=2026-03-31&page=1",
        "impact_score": 0,
        "tags": []
      },
      {
        "source": "비즈워치",
        "title": "유가 급등·미 반도체 급락에 코스피 하락 출발…\"장중 낙폭 축소 기대\"",
        "published_at": "2026-03-31 09:26:15",
        "url": "https://finance.naver.com/news/news_read.naver?article_id=0000045824&office_id=648&mode=mainnews&type=&date=2026-03-31&page=1",
        "impact_score": -4,
        "tags": [
          "-급락",
          "-축소"
        ]
      },
      {
        "source": "조선일보",
        "title": "코스피 3%대 급락… 삼성전자 16만·SK하이닉스 81만원대로 ‘와르르’",
        "published_at": "2026-03-31 09:24:14",
        "url": "https://finance.naver.com/news/news_read.naver?article_id=0003967868&office_id=023&mode=mainnews&type=&date=2026-03-31&page=1",
        "impact_score": -3,
        "tags": [
          "-급락"
        ]
      },
      {
        "source": "머니투데이",
        "title": "미국 반도체 급락·유가 급등...삼전닉스 '휘청' 코스피 5000대 후퇴",
        "published_at": "2026-03-31 09:22:56",
        "url": "https://finance.naver.com/news/news_read.naver?article_id=0005337371&office_id=008&mode=mainnews&type=&date=2026-03-31&page=1",
        "impact_score": -3,
        "tags": [
          "-급락"
        ]
      },
      {
        "source": "뉴스1",
        "title": "삼성전자, 17만원도 깨졌다…SK하이닉스 7.22%↓ [핫종목]",
        "published_at": "2026-03-31 09:22:50",
        "url": "https://finance.naver.com/news/news_read.naver?article_id=0008859106&office_id=421&mode=mainnews&type=&date=2026-03-31&page=1",
        "impact_score": 0,
        "tags": []
      },
      {
        "source": "데일리안",
        "title": "바이오가 대세…‘TIGER 기술이전바이오액티브’ 순자산 1000억 돌파",
        "published_at": "2026-03-31 09:21:13",
        "url": "https://finance.naver.com/news/news_read.naver?article_id=0003075033&office_id=119&mode=mainnews&type=&date=2026-03-31&page=1",
        "impact_score": 0,
        "tags": []
      },
      {
        "source": "이데일리",
        "title": "코스피·코스닥 하락 출발…삼전·하닉·삼천당 줄줄이 약세",
        "published_at": "2026-03-31 09:21:10",
        "url": "https://finance.naver.com/news/news_read.naver?article_id=0006246047&office_id=018&mode=mainnews&type=&date=2026-03-31&page=1",
        "impact_score": 0,
        "tags": []
      },
      {
        "source": "한국경제TV",
        "title": "\"당분간 계좌 안 보려고요\"…삼전·닉스 낙관론 '머쓱'",
        "published_at": "2026-03-31 09:20:18",
        "url": "https://finance.naver.com/news/news_read.naver?article_id=0001247238&office_id=215&mode=mainnews&type=&date=2026-03-31&page=1",
        "impact_score": 0,
        "tags": []
      },
      {
        "source": "디지털타임스",
        "title": "코스피, 글로벌 반도체 업황 위축 우려에 5140선 약세 출발…SK하닉 6%↓",
        "published_at": "2026-03-31 09:17:50",
        "url": "https://finance.naver.com/news/news_read.naver?article_id=0003019030&office_id=029&mode=mainnews&type=&date=2026-03-31&page=1",
        "impact_score": 0,
        "tags": []
      },
      {
        "source": "더팩트",
        "title": "중동 리스크 다시 고개…코스피, 5130선 후퇴",
        "published_at": "2026-03-31 09:17:11",
        "url": "https://finance.naver.com/news/news_read.naver?article_id=0000486723&office_id=629&mode=mainnews&type=&date=2026-03-31&page=1",
        "impact_score": -2,
        "tags": [
          "-리스크"
        ]
      },
      {
        "source": "머니투데이",
        "title": "터보퀀트, 오히려 기회라는데…\"반도체주 녹는다\" 삼전·SK하닉 '뚝'",
        "published_at": "2026-03-31 09:10:31",
        "url": "https://finance.naver.com/news/news_read.naver?article_id=0005337358&office_id=008&mode=mainnews&type=&date=2026-03-31&page=1",
        "impact_score": 0,
        "tags": []
      },
      {
        "source": "아시아경제",
        "title": "우리자산운용, 두산그룹포커스 ETF 상장…원전·로봇·반도체 총망라",
        "published_at": "2026-03-31 09:03:57",
        "url": "https://finance.naver.com/news/news_read.naver?article_id=0005742414&office_id=277&mode=mainnews&type=&date=2026-03-31&page=1",
        "impact_score": 0,
        "tags": []
      },
      {
        "source": "더팩트",
        "title": "현대기술투자, CB 또 태웠다…적자 '만월경'에 수혈한 배경은",
        "published_at": "2026-03-31 09:01:11",
        "url": "https://finance.naver.com/news/news_read.naver?article_id=0000486714&office_id=629&mode=mainnews&type=&date=2026-03-31&page=1",
        "impact_score": -3,
        "tags": [
          "-적자"
        ]
      },
      {
        "source": "뉴스1",
        "title": "리서치알음 \"한국주강, 동전주 퇴출이 재평가 기회…목표가 3500원\"",
        "published_at": "2026-03-31 08:58:43",
        "url": "https://finance.naver.com/news/news_read.naver?article_id=0008859018&office_id=421&mode=mainnews&type=&date=2026-03-31&page=1",
        "impact_score": 0,
        "tags": []
      },
      {
        "source": "파이낸셜뉴스",
        "title": "삼성운용 ‘KODEX 미국AI광통신네트워크’ 신규 상장",
        "published_at": "2026-03-31 08:55:11",
        "url": "https://finance.naver.com/news/news_read.naver?article_id=0005499833&office_id=014&mode=mainnews&type=&date=2026-03-31&page=1",
        "impact_score": 0,
        "tags": []
      }
    ],
    "dart": [
      {
        "corp_name": "씨티알로보틱스",
        "title": "감사보고서 (2025.12)",
        "published_at": "20260331",
        "url": "https://dart.fss.or.kr/dsaf001/main.do?rcpNo=20260331000442",
        "impact_score": 0,
        "tags": []
      },
      {
        "corp_name": "티앤에스엔지니어링",
        "title": "감사보고서 (2025.12)",
        "published_at": "20260331",
        "url": "https://dart.fss.or.kr/dsaf001/main.do?rcpNo=20260331000441",
        "impact_score": 0,
        "tags": []
      },
      {
        "corp_name": "이에스티",
        "title": "감사보고서 (2025.12)",
        "published_at": "20260331",
        "url": "https://dart.fss.or.kr/dsaf001/main.do?rcpNo=20260331000440",
        "impact_score": 0,
        "tags": []
      },
      {
        "corp_name": "세화금속공업",
        "title": "감사보고서 (2025.12)",
        "published_at": "20260331",
        "url": "https://dart.fss.or.kr/dsaf001/main.do?rcpNo=20260331000439",
        "impact_score": 0,
        "tags": []
      },
      {
        "corp_name": "대화이앤씨건설",
        "title": "감사보고서 (2025.12)",
        "published_at": "20260331",
        "url": "https://dart.fss.or.kr/dsaf001/main.do?rcpNo=20260331000438",
        "impact_score": 0,
        "tags": []
      },
      {
        "corp_name": "삼양라운드스퀘어",
        "title": "연결감사보고서 (2025.12)",
        "published_at": "20260331",
        "url": "https://dart.fss.or.kr/dsaf001/main.do?rcpNo=20260331000437",
        "impact_score": 0,
        "tags": []
      },
      {
        "corp_name": "신대한",
        "title": "감사보고서 (2025.12)",
        "published_at": "20260331",
        "url": "https://dart.fss.or.kr/dsaf001/main.do?rcpNo=20260331000436",
        "impact_score": 0,
        "tags": []
      },
      {
        "corp_name": "아스트로젠",
        "title": "사업보고서 (2025.12)",
        "published_at": "20260331",
        "url": "https://dart.fss.or.kr/dsaf001/main.do?rcpNo=20260331000435",
        "impact_score": 0,
        "tags": []
      },
      {
        "corp_name": "성안당",
        "title": "감사보고서 (2025.12)",
        "published_at": "20260331",
        "url": "https://dart.fss.or.kr/dsaf001/main.do?rcpNo=20260331000434",
        "impact_score": 0,
        "tags": []
      },
      {
        "corp_name": "삼양라운드스퀘어",
        "title": "감사보고서 (2025.12)",
        "published_at": "20260331",
        "url": "https://dart.fss.or.kr/dsaf001/main.do?rcpNo=20260331000433",
        "impact_score": 0,
        "tags": []
      },
      {
        "corp_name": "삼진콘크리트",
        "title": "감사보고서 (2025.12)",
        "published_at": "20260331",
        "url": "https://dart.fss.or.kr/dsaf001/main.do?rcpNo=20260331000432",
        "impact_score": 0,
        "tags": []
      },
      {
        "corp_name": "에이치피아이",
        "title": "감사보고서 (2025.12)",
        "published_at": "20260331",
        "url": "https://dart.fss.or.kr/dsaf001/main.do?rcpNo=20260331000431",
        "impact_score": 0,
        "tags": []
      },
      {
        "corp_name": "엠에스종합건설",
        "title": "감사보고서 (2025.12)",
        "published_at": "20260331",
        "url": "https://dart.fss.or.kr/dsaf001/main.do?rcpNo=20260331000430",
        "impact_score": 0,
        "tags": []
      },
      {
        "corp_name": "이건그린텍",
        "title": "감사보고서 (2025.12)",
        "published_at": "20260331",
        "url": "https://dart.fss.or.kr/dsaf001/main.do?rcpNo=20260331000429",
        "impact_score": 0,
        "tags": []
      },
      {
        "corp_name": "강남대성학원",
        "title": "감사보고서 (2025.12)",
        "published_at": "20260331",
        "url": "https://dart.fss.or.kr/dsaf001/main.do?rcpNo=20260331000428",
        "impact_score": 0,
        "tags": []
      },
      {
        "corp_name": "비욘드아이",
        "title": "감사보고서 (2025.12)",
        "published_at": "20260331",
        "url": "https://dart.fss.or.kr/dsaf001/main.do?rcpNo=20260331000427",
        "impact_score": 0,
        "tags": []
      },
      {
        "corp_name": "성우철강",
        "title": "감사보고서 (2025.12)",
        "published_at": "20260331",
        "url": "https://dart.fss.or.kr/dsaf001/main.do?rcpNo=20260331000425",
        "impact_score": 0,
        "tags": []
      },
      {
        "corp_name": "홍성산업",
        "title": "감사보고서 (2025.12)",
        "published_at": "20260331",
        "url": "https://dart.fss.or.kr/dsaf001/main.do?rcpNo=20260331000424",
        "impact_score": 0,
        "tags": []
      },
      {
        "corp_name": "서울신문사",
        "title": "감사보고서 (2025.12)",
        "published_at": "20260331",
        "url": "https://dart.fss.or.kr/dsaf001/main.do?rcpNo=20260331000423",
        "impact_score": 0,
        "tags": []
      },
      {
        "corp_name": "에이티지씨",
        "title": "[기재정정]사업보고서 (2025.12)",
        "published_at": "20260331",
        "url": "https://dart.fss.or.kr/dsaf001/main.do?rcpNo=20260331000422",
        "impact_score": 0,
        "tags": [
          "-정정"
        ]
      },
      {
        "corp_name": "바나플",
        "title": "감사보고서 (2025.12)",
        "published_at": "20260331",
        "url": "https://dart.fss.or.kr/dsaf001/main.do?rcpNo=20260331000421",
        "impact_score": 0,
        "tags": []
      },
      {
        "corp_name": "신복개발",
        "title": "감사보고서 (2025.12)",
        "published_at": "20260331",
        "url": "https://dart.fss.or.kr/dsaf001/main.do?rcpNo=20260331000420",
        "impact_score": 0,
        "tags": []
      },
      {
        "corp_name": "발렉스서비스",
        "title": "연결감사보고서 (2025.12)",
        "published_at": "20260331",
        "url": "https://dart.fss.or.kr/dsaf001/main.do?rcpNo=20260331000419",
        "impact_score": 0,
        "tags": []
      },
      {
        "corp_name": "티시스",
        "title": "동일인등출자계열회사와의상품ㆍ용역거래변경",
        "published_at": "20260331",
        "url": "https://dart.fss.or.kr/dsaf001/main.do?rcpNo=20260331000417",
        "impact_score": 0,
        "tags": []
      },
      {
        "corp_name": "모트라스",
        "title": "감사보고서 (2025.12)",
        "published_at": "20260331",
        "url": "https://dart.fss.or.kr/dsaf001/main.do?rcpNo=20260331000416",
        "impact_score": 0,
        "tags": []
      },
      {
        "corp_name": "엘비엠",
        "title": "감사보고서 (2025.12)",
        "published_at": "20260331",
        "url": "https://dart.fss.or.kr/dsaf001/main.do?rcpNo=20260331000415",
        "impact_score": 0,
        "tags": []
      },
      {
        "corp_name": "덕신하우징",
        "title": "감사보고서 (2025.12)",
        "published_at": "20260331",
        "url": "https://dart.fss.or.kr/dsaf001/main.do?rcpNo=20260331000414",
        "impact_score": 0,
        "tags": []
      },
      {
        "corp_name": "발렉스서비스",
        "title": "감사보고서 (2025.12)",
        "published_at": "20260331",
        "url": "https://dart.fss.or.kr/dsaf001/main.do?rcpNo=20260331000413",
        "impact_score": 0,
        "tags": []
      },
      {
        "corp_name": "한화손해보험",
        "title": "[기재정정]특수관계인과의내부거래",
        "published_at": "20260331",
        "url": "https://dart.fss.or.kr/dsaf001/main.do?rcpNo=20260331000412",
        "impact_score": 0,
        "tags": [
          "-정정"
        ]
      },
      {
        "corp_name": "웅진컴퍼스",
        "title": "감사보고서 (2025.12)",
        "published_at": "20260331",
        "url": "https://dart.fss.or.kr/dsaf001/main.do?rcpNo=20260331000410",
        "impact_score": 0,
        "tags": []
      },
      {
        "corp_name": "프로톡스",
        "title": "사업보고서 (2025.12)",
        "published_at": "20260331",
        "url": "https://dart.fss.or.kr/dsaf001/main.do?rcpNo=20260331000408",
        "impact_score": 0,
        "tags": []
      },
      {
        "corp_name": "동양엠더블유",
        "title": "감사보고서 (2025.12)",
        "published_at": "20260331",
        "url": "https://dart.fss.or.kr/dsaf001/main.do?rcpNo=20260331000407",
        "impact_score": 0,
        "tags": []
      },
      {
        "corp_name": "제이에스원",
        "title": "동일인등출자계열회사와의상품ㆍ용역거래",
        "published_at": "20260331",
        "url": "https://dart.fss.or.kr/dsaf001/main.do?rcpNo=20260331000406",
        "impact_score": 0,
        "tags": []
      },
      {
        "corp_name": "삼우이피",
        "title": "감사보고서 (2025.12)",
        "published_at": "20260331",
        "url": "https://dart.fss.or.kr/dsaf001/main.do?rcpNo=20260331000405",
        "impact_score": 0,
        "tags": []
      },
      {
        "corp_name": "유디프라퍼티",
        "title": "감사보고서 (2025.12)",
        "published_at": "20260331",
        "url": "https://dart.fss.or.kr/dsaf001/main.do?rcpNo=20260331000404",
        "impact_score": 0,
        "tags": []
      },
      {
        "corp_name": "이롬넷",
        "title": "감사보고서 (2025.12)",
        "published_at": "20260331",
        "url": "https://dart.fss.or.kr/dsaf001/main.do?rcpNo=20260331000402",
        "impact_score": 0,
        "tags": []
      },
      {
        "corp_name": "다인정공",
        "title": "감사보고서 (2025.12)",
        "published_at": "20260331",
        "url": "https://dart.fss.or.kr/dsaf001/main.do?rcpNo=20260331000401",
        "impact_score": 0,
        "tags": []
      },
      {
        "corp_name": "학산",
        "title": "연결감사보고서 (2025.12)",
        "published_at": "20260331",
        "url": "https://dart.fss.or.kr/dsaf001/main.do?rcpNo=20260331000399",
        "impact_score": 0,
        "tags": []
      },
      {
        "corp_name": "유니티테크놀로지스코리아",
        "title": "감사보고서 (2025.12)",
        "published_at": "20260331",
        "url": "https://dart.fss.or.kr/dsaf001/main.do?rcpNo=20260331000398",
        "impact_score": 0,
        "tags": []
      },
      {
        "corp_name": "대드",
        "title": "감사보고서 (2025.12)",
        "published_at": "20260331",
        "url": "https://dart.fss.or.kr/dsaf001/main.do?rcpNo=20260331000397",
        "impact_score": 0,
        "tags": []
      }
    ],
    "news_count": 20,
    "dart_count": 40
  },
  "sentiment": {
    "raw_score": -30.58,
    "score": 29.6,
    "raw_label": "bearish",
    "label": "경계",
    "range_key": "caution",
    "range_rule": "20~39.9는 경계 구간",
    "interpretation": "약세 압력과 변동성 우려가 우세한 상태입니다.",
    "confidence": 81,
    "market_score": -7.81,
    "news_score": -16.4,
    "dart_score": 0.0,
    "sector_score": 0.0,
    "normalized_components": {
      "market": -0.7407,
      "news": -3.0,
      "dart": 0.0,
      "sector": -0.6745
    },
    "weights": {
      "market": 0.3,
      "news": 0.3,
      "dart": 0.25,
      "sector": 0.15
    },
    "model_version": "v2.0-calibrated",
    "calibration_metric": 0.1081,
    "calibration_samples": 37,
    "score_breakdown": {
      "market": -7.81,
      "news": -16.4,
      "dart": 0.0,
      "sector": 0.0
    },
    "tooltip_breakdown": "시장 -7.81 / 뉴스 -16.4 / 공시 0.0 / 섹터 0.0",
    "data_quality": {
      "live_indexes": 9,
      "event_count": 60,
      "sector_confirmed": 0,
      "score": 81,
      "basis": "지표 9/9, 이벤트 60건, 섹터확인 0건"
    },
    "confidence_tooltip": [
      "신뢰도 안내",
      "신뢰도는 예측 적중률이 아니라, 현재 점수 계산에 사용된 데이터의 충실도를 의미합니다.",
      "현재 신뢰도: 81%",
      "해석: 데이터 커버리지가 높은 상태입니다.",
      "기준: 지표 9/9, 이벤트 60건, 섹터확인 0건",
      "주의: 이 값이 미래 방향 적중률을 직접 뜻하지는 않습니다."
    ]
  },
  "key_points": [
    "KOSPI는 5,145.69로 131.61포인트(2.49%) 하락하며 전쟁 이후 최저치를 기록했습니다.",
    "KOSDAQ은 1,078.66으로 28.39포인트(2.56%) 떨어져 **반도체** 주식의 급락이 영향을 미쳤습니다.",
    "센티먼트는 29.6점으로 **경계** 구간에 있으며, 시장은 -7.81로 부정적인 흐름을 보이고 있습니다."
  ],
  "watchpoint": "오늘의 핵심 관전 포인트: 반도체 주식의 향후 움직임이 시장에 미치는 영향 주목.",
  "day_over_day": [
    "전일 동시간 대비 **센티먼트 -3.60p** 변화로 현재 점수는 29.6점입니다.",
    "리스크 축은 **VIX 3.17**, **달러원 15.36** 만큼 변동했습니다.",
    "이벤트 발생량은 전일 대비 **+0건** 차이로 뉴스/공시 민감도를 점검할 구간입니다."
  ],
  "sector_rotation": {
    "scores": [
      {
        "sector": "2차전지",
        "mentions": 0,
        "event_score": 0.0,
        "price_confirmation": 0.0,
        "breadth": 0,
        "final_score": 0.0,
        "confidence": 35,
        "price_confirmed": false,
        "representatives": [],
        "matched_titles": []
      },
      {
        "sector": "금융",
        "mentions": 1,
        "event_score": 0.0,
        "price_confirmation": 0.0,
        "breadth": 0,
        "final_score": 0.0,
        "confidence": 45,
        "price_confirmed": false,
        "representatives": [],
        "matched_titles": [
          "[기재정정]특수관계인과의내부거래"
        ]
      },
      {
        "sector": "방산",
        "mentions": 0,
        "event_score": 0.0,
        "price_confirmation": 0.0,
        "breadth": 0,
        "final_score": 0.0,
        "confidence": 35,
        "price_confirmed": false,
        "representatives": [],
        "matched_titles": []
      },
      {
        "sector": "바이오",
        "mentions": 3,
        "event_score": -3.0,
        "price_confirmation": 0.0,
        "breadth": -1,
        "final_score": -1.08,
        "confidence": 65,
        "price_confirmed": false,
        "representatives": [],
        "matched_titles": [
          "“고점 왔나”…20% 급락한 삼천당제약, 황제주 반납 [이런국장 저런주식]",
          "“코스닥 핵심”…TIGER 기술이전바이오액티브, 순자산 1000억 돌파",
          "바이오가 대세…‘TIGER 기술이전바이오액티브’ 순자산 1000억 돌파"
        ]
      },
      {
        "sector": "에너지",
        "mentions": 2,
        "event_score": -7.0,
        "price_confirmation": 0.0,
        "breadth": -2,
        "final_score": -2.42,
        "confidence": 55,
        "price_confirmed": false,
        "representatives": [],
        "matched_titles": [
          "유가 급등·미 반도체 급락에 코스피 하락 출발…\"장중 낙폭 축소 기대\"",
          "미국 반도체 급락·유가 급등...삼전닉스 '휘청' 코스피 5000대 후퇴"
        ]
      },
      {
        "sector": "반도체",
        "mentions": 8,
        "event_score": -13.0,
        "price_confirmation": 0.0,
        "breadth": -4,
        "final_score": -3.0,
        "confidence": 75,
        "price_confirmed": false,
        "representatives": [],
        "matched_titles": [
          "코스피, 전쟁 이후 장중 최저치로 떨어져…반도체株 급락",
          "유가 급등·미 반도체 급락에 코스피 하락 출발…\"장중 낙폭 축소 기대\"",
          "코스피 3%대 급락… 삼성전자 16만·SK하이닉스 81만원대로 ‘와르르’"
        ]
      }
    ],
    "strong": [],
    "weak": [
      {
        "sector": "반도체",
        "mentions": 8,
        "event_score": -13.0,
        "price_confirmation": 0.0,
        "breadth": -4,
        "final_score": -3.0,
        "confidence": 75,
        "price_confirmed": false,
        "representatives": [],
        "matched_titles": [
          "코스피, 전쟁 이후 장중 최저치로 떨어져…반도체株 급락",
          "유가 급등·미 반도체 급락에 코스피 하락 출발…\"장중 낙폭 축소 기대\"",
          "코스피 3%대 급락… 삼성전자 16만·SK하이닉스 81만원대로 ‘와르르’"
        ]
      },
      {
        "sector": "에너지",
        "mentions": 2,
        "event_score": -7.0,
        "price_confirmation": 0.0,
        "breadth": -2,
        "final_score": -2.42,
        "confidence": 55,
        "price_confirmed": false,
        "representatives": [],
        "matched_titles": [
          "유가 급등·미 반도체 급락에 코스피 하락 출발…\"장중 낙폭 축소 기대\"",
          "미국 반도체 급락·유가 급등...삼전닉스 '휘청' 코스피 5000대 후퇴"
        ]
      },
      {
        "sector": "바이오",
        "mentions": 3,
        "event_score": -3.0,
        "price_confirmation": 0.0,
        "breadth": -1,
        "final_score": -1.08,
        "confidence": 65,
        "price_confirmed": false,
        "representatives": [],
        "matched_titles": [
          "“고점 왔나”…20% 급락한 삼천당제약, 황제주 반납 [이런국장 저런주식]",
          "“코스닥 핵심”…TIGER 기술이전바이오액티브, 순자산 1000억 돌파",
          "바이오가 대세…‘TIGER 기술이전바이오액티브’ 순자산 1000억 돌파"
        ]
      }
    ],
    "basis": "이벤트 점수 + 대표 종목 수익률 확인 결합"
  },
  "reliability": {
    "evaluated": 125,
    "hit_rate": "34.4%",
    "false_alarm_rate": "65.6%",
    "by_label": {
      "bullish": "24.0%",
      "bearish": "29.0%",
      "neutral": "40.6%"
    },
    "basis": "현재 시그널 이후 다음 슬롯의 KOSPI/KOSDAQ 변동률 개선 여부 기준"
  },
  "heatmap": {
    "slots": [
      "08:30",
      "09:30",
      "10:30",
      "11:30",
      "12:30",
      "13:30",
      "14:30",
      "15:30"
    ],
    "rows": [
      {
        "day": "03-25",
        "scores": [
          {
            "slot": "08:30",
            "text": "33",
            "color": "#dbeafe",
            "state": "caution"
          },
          {
            "slot": "09:30",
            "text": "70",
            "color": "#fee2e2",
            "state": "bullish"
          },
          {
            "slot": "10:30",
            "text": "-",
            "color": "#f8fafc",
            "state": "missing"
          },
          {
            "slot": "11:30",
            "text": "50",
            "color": "#e2e8f0",
            "state": "neutral"
          },
          {
            "slot": "12:30",
            "text": "45",
            "color": "#e2e8f0",
            "state": "neutral"
          },
          {
            "slot": "13:30",
            "text": "43",
            "color": "#e2e8f0",
            "state": "neutral"
          },
          {
            "slot": "14:30",
            "text": "67",
            "color": "#fee2e2",
            "state": "bullish"
          },
          {
            "slot": "15:30",
            "text": "62",
            "color": "#fee2e2",
            "state": "bullish"
          }
        ]
      },
      {
        "day": "03-26",
        "scores": [
          {
            "slot": "08:30",
            "text": "75",
            "color": "#fee2e2",
            "state": "bullish"
          },
          {
            "slot": "09:30",
            "text": "44",
            "color": "#e2e8f0",
            "state": "neutral"
          },
          {
            "slot": "10:30",
            "text": "-",
            "color": "#f8fafc",
            "state": "missing"
          },
          {
            "slot": "11:30",
            "text": "52",
            "color": "#e2e8f0",
            "state": "neutral"
          },
          {
            "slot": "12:30",
            "text": "44",
            "color": "#e2e8f0",
            "state": "neutral"
          },
          {
            "slot": "13:30",
            "text": "-",
            "color": "#f8fafc",
            "state": "missing"
          },
          {
            "slot": "14:30",
            "text": "30",
            "color": "#dbeafe",
            "state": "caution"
          },
          {
            "slot": "15:30",
            "text": "48",
            "color": "#e2e8f0",
            "state": "neutral"
          }
        ]
      },
      {
        "day": "03-27",
        "scores": [
          {
            "slot": "08:30",
            "text": "40",
            "color": "#e2e8f0",
            "state": "neutral"
          },
          {
            "slot": "09:30",
            "text": "33",
            "color": "#dbeafe",
            "state": "caution"
          },
          {
            "slot": "10:30",
            "text": "-",
            "color": "#f8fafc",
            "state": "missing"
          },
          {
            "slot": "11:30",
            "text": "39",
            "color": "#dbeafe",
            "state": "caution"
          },
          {
            "slot": "12:30",
            "text": "39",
            "color": "#dbeafe",
            "state": "caution"
          },
          {
            "slot": "13:30",
            "text": "-",
            "color": "#f8fafc",
            "state": "missing"
          },
          {
            "slot": "14:30",
            "text": "37",
            "color": "#dbeafe",
            "state": "caution"
          },
          {
            "slot": "15:30",
            "text": "36",
            "color": "#dbeafe",
            "state": "caution"
          }
        ]
      },
      {
        "day": "03-30",
        "scores": [
          {
            "slot": "08:30",
            "text": "47",
            "color": "#e2e8f0",
            "state": "neutral"
          },
          {
            "slot": "09:30",
            "text": "-",
            "color": "#f8fafc",
            "state": "missing"
          },
          {
            "slot": "10:30",
            "text": "33",
            "color": "#dbeafe",
            "state": "caution"
          },
          {
            "slot": "11:30",
            "text": "44",
            "color": "#e2e8f0",
            "state": "neutral"
          },
          {
            "slot": "12:30",
            "text": "44",
            "color": "#e2e8f0",
            "state": "neutral"
          },
          {
            "slot": "13:30",
            "text": "-",
            "color": "#f8fafc",
            "state": "missing"
          },
          {
            "slot": "14:30",
            "text": "34",
            "color": "#dbeafe",
            "state": "caution"
          },
          {
            "slot": "15:30",
            "text": "28",
            "color": "#dbeafe",
            "state": "caution"
          }
        ]
      },
      {
        "day": "03-31",
        "scores": [
          {
            "slot": "08:30",
            "text": "48",
            "color": "#e2e8f0",
            "state": "neutral"
          },
          {
            "slot": "09:30",
            "text": "30",
            "color": "#dbeafe",
            "state": "caution"
          },
          {
            "slot": "10:30",
            "text": "-",
            "color": "#f8fafc",
            "state": "missing"
          },
          {
            "slot": "11:30",
            "text": "-",
            "color": "#f8fafc",
            "state": "missing"
          },
          {
            "slot": "12:30",
            "text": "-",
            "color": "#f8fafc",
            "state": "missing"
          },
          {
            "slot": "13:30",
            "text": "-",
            "color": "#f8fafc",
            "state": "missing"
          },
          {
            "slot": "14:30",
            "text": "-",
            "color": "#f8fafc",
            "state": "missing"
          },
          {
            "slot": "15:30",
            "text": "-",
            "color": "#f8fafc",
            "state": "missing"
          }
        ]
      }
    ],
    "timeline": [
      {
        "time": "03-27 11:17",
        "score": 39.4,
        "label": "경계",
        "color": "#dbeafe"
      },
      {
        "time": "03-27 12:34",
        "score": 39.2,
        "label": "경계",
        "color": "#dbeafe"
      },
      {
        "time": "03-27 14:59",
        "score": 37.0,
        "label": "경계",
        "color": "#dbeafe"
      },
      {
        "time": "03-27 15:51",
        "score": 35.9,
        "label": "경계",
        "color": "#dbeafe"
      },
      {
        "time": "03-30 08:45",
        "score": 47.1,
        "label": "중립",
        "color": "#e2e8f0"
      },
      {
        "time": "03-30 10:03",
        "score": 33.2,
        "label": "경계",
        "color": "#dbeafe"
      },
      {
        "time": "03-30 11:17",
        "score": 44.3,
        "label": "중립",
        "color": "#e2e8f0"
      },
      {
        "time": "03-30 12:39",
        "score": 44.5,
        "label": "중립",
        "color": "#e2e8f0"
      },
      {
        "time": "03-30 14:17",
        "score": 33.7,
        "label": "경계",
        "color": "#dbeafe"
      },
      {
        "time": "03-30 16:03",
        "score": 28.3,
        "label": "경계",
        "color": "#dbeafe"
      },
      {
        "time": "03-31 08:46",
        "score": 47.8,
        "label": "중립",
        "color": "#e2e8f0"
      },
      {
        "time": "03-31 10:00",
        "score": 29.6,
        "label": "경계",
        "color": "#dbeafe"
      }
    ],
    "legend": [
      {
        "name": "강한 우호 80+",
        "color": "#fecaca"
      },
      {
        "name": "우호 60~79",
        "color": "#fee2e2"
      },
      {
        "name": "중립 40~59",
        "color": "#e2e8f0"
      },
      {
        "name": "경계 20~39",
        "color": "#dbeafe"
      },
      {
        "name": "강한 경계 0~19",
        "color": "#bfdbfe"
      },
      {
        "name": "결측",
        "color": "#f8fafc"
      }
    ]
  },
  "calibration": {
    "stats": {
      "market": {
        "median": -0.48,
        "scale": 9.8964,
        "p02": -12.0,
        "p98": 12.0
      },
      "news": {
        "median": 1.6,
        "scale": 3.8548,
        "p02": -16.0,
        "p98": 8.775
      },
      "dart": {
        "median": 0.0,
        "scale": 4.4478,
        "p02": -17.0,
        "p98": 9.5
      },
      "sector": {
        "median": 0.36,
        "scale": 0.5337,
        "p02": -0.2,
        "p98": 6.74
      }
    },
    "weights": {
      "market": 0.3,
      "news": 0.3,
      "dart": 0.25,
      "sector": 0.15
    },
    "metric": 0.1081,
    "samples": 37,
    "model_version": "v2.0-calibrated",
    "mode": "calibrated_grid_search"
  },
  "validation_basis": "현재 시그널 이후 다음 슬롯의 KOSPI/KOSDAQ 변동률 개선 여부 기준"
}