{
  "timestamp": "2026-03-10 18:12:32",
  "edition_title": "Evening Briefing: 오늘 국장 마감 & 미장 프리뷰",
  "headline": "코스피 연중 최고치 경신",
  "summary_items": [
    "[한국 시장]",
    "**코스피**가 5,532.59로 5.35% 상승하며 연중 최고치를 경신했습니다. 이는 외국인 및 기관의 **매수세** 유입에 기인합니다.",
    "코스닥도 **1,137.68**로 3.21% 상승, 바이오 및 IT 섹터에서 투자자가 **긍정적 반응**을 보이며 기업 가치에 대한 기대감이 높아졌습니다.",
    "**달러원 지수**가 1,470.09로 하락하며 원화가치가 상승했습니다. 이는 해외 자금 유입에 **긍정적 영향을 줄** 것으로 보입니다.",
    "[미국 시장]",
    "S&P500가 **6,795.99**로 0.83% 상승, 긍정적인 경제 지표가 주효하며 투자 심리를 **향상시키고 있습니다**.",
    "**VIX 지수**가 23.66으로 하락했습니다. 이는 시장 **변동성 감소**를 나타내며 안정적인 투자 환경을 조성합니다.",
    "오늘의 **핵심 관전 포인트**: **VIX**(23.66)가 반등하면 단기 변동성 재확대를 염두에 두고, **미10년물**(4.14)과 **달러원**(1,470.09)이 동반 상승하면 고밸류 추격 대신 방어주와 현금 비중을 병행 점검하세요."
  ],
  "indexes": {
    "kospi": {
      "price": "5,532.59",
      "change": "▲ 280.72 (+5.35%)",
      "color": "#ef4444",
      "trend": "상승"
    },
    "kosdaq": {
      "price": "1,137.68",
      "change": "▲ 35.40 (+3.21%)",
      "color": "#ef4444",
      "trend": "상승"
    },
    "sp500": {
      "price": "6,795.99",
      "change": "▲ 55.97 (+0.83%)",
      "color": "#ef4444",
      "trend": "상승"
    },
    "dow": {
      "price": "47,740.80",
      "change": "▲ 239.25 (+0.50%)",
      "color": "#ef4444",
      "trend": "상승"
    },
    "nasdaq": {
      "price": "22,695.95",
      "change": "▲ 308.27 (+1.38%)",
      "color": "#ef4444",
      "trend": "상승"
    },
    "ewy": {
      "price": "133.89",
      "change": "▲ 7.16 (+5.65%)",
      "color": "#ef4444",
      "trend": "상승"
    },
    "vix": {
      "price": "23.66",
      "change": "▼ 1.84 (-7.22%)",
      "color": "#3b82f6",
      "trend": "하락"
    },
    "usdkrw": {
      "price": "1,470.09",
      "change": "▼ 13.80 (-0.93%)",
      "color": "#3b82f6",
      "trend": "하락"
    },
    "us10y": {
      "price": "4.14",
      "change": "▲ 0.00 (+0.07%)",
      "color": "#ef4444",
      "trend": "상승"
    },
    "wti": {
      "price": "88.49",
      "change": "▼ 6.28 (-6.63%)",
      "color": "#3b82f6",
      "trend": "하락"
    }
  },
  "cover_image": "cover.png",
  "generate_ai_image": true,
  "run_source": "schedule"
}